h_sample_math_mcp/__init__.py
h_sample_math_mcp/__main__.py
h_sample_math_mcp/tools.py
h_sample_math_mcp-0.1.0.dist-info/METADATA
h_sample_math_mcp-0.1.0.dist-info/WHEEL
h_sample_math_mcp-0.1.0.dist-info/entry_points.txt
h_sample_math_mcp-0.1.0.dist-info/RECORD
