Metadata-Version: 2.4
Name: h-sample-math-mcp
Version: 0.1.0
Summary: Add your description here
Author-email: harshitha <harshithav79@yahoo.com>
Requires-Python: >=3.13
Requires-Dist: mcp[cli]>=1.12.3
Requires-Dist: sympy>=1.14.0
